pygeodata/__init__.py
pygeodata/config.py
pygeodata/load.py
pygeodata/loader.py
pygeodata/options.py
pygeodata/paths.py
pygeodata/types.py
pygeodata/utils.py
pygeodata/drivers/__init__.py
pygeodata/drivers/xarray.py
pygeodata/processors/__init__.py
pygeodata/processors/rasterizer.py
pygeodata/processors/reprojection.py
pygeodata-0.0.1.dist-info/licenses/LICENSE
pygeodata-0.0.1.dist-info/METADATA
pygeodata-0.0.1.dist-info/WHEEL
pygeodata-0.0.1.dist-info/top_level.txt
pygeodata-0.0.1.dist-info/RECORD
