Metadata-Version: 2.4
Name: pygeodata
Version: 0.0.1
Summary: Lightweight framework for geospatial data access and processing
Author-email: Jasper Roebroek <roebroek.jasper@gmail.com>
License: MIT
Classifier: Programming Language :: Python :: 3
Requires-Python: >=3.12
License-File: LICENSE
Requires-Dist: rioxarray
Requires-Dist: geopandas
Requires-Dist: dask
Requires-Dist: zarr
Provides-Extra: test
Requires-Dist: pytest; extra == "test"
Dynamic: license-file
